myccc/__init__.py
myccc/media.py
myccc/schedule.py
myccc-0.3.0.dist-info/LICENSE
myccc-0.3.0.dist-info/METADATA
myccc-0.3.0.dist-info/WHEEL
myccc-0.3.0.dist-info/RECORD
